pylibtemplate/__init__.py
pylibtemplate/version.py
pylibtemplate-0.0.8.dist-info/licenses/LICENSE
pylibtemplate-0.0.8.dist-info/METADATA
pylibtemplate-0.0.8.dist-info/WHEEL
pylibtemplate-0.0.8.dist-info/entry_points.txt
pylibtemplate-0.0.8.dist-info/top_level.txt
pylibtemplate-0.0.8.dist-info/RECORD
