Metadata-Version: 2.4
Name: pylibtemplate
Version: 0.0.8
Summary: A Python library that generates `git` repository templates for building Python libraries that are suitable for publication on PyPI.
Author-email: Matthew Fitzpatrick <matthew.rc.fitzpatrick@gmail.com>
Project-URL: Homepage, https://mrfitzpa.github.io/pylibtemplate
Project-URL: Repository, https://github.com/mrfitzpa/pylibtemplate
Keywords: library,template
Classifier: License :: OSI Approved :: GNU General Public License v3 (GPLv3)
Classifier: Development Status :: 5 - Production/Stable
Classifier: Intended Audience :: Developers
Classifier: Programming Language :: Python
Classifier: Programming Language :: Python :: 3
Classifier: Programming Language :: Python :: 3.9
Classifier: Programming Language :: Python :: 3.10
Classifier: Programming Language :: Python :: 3.11
Classifier: Programming Language :: Python :: 3.12
Classifier: Operating System :: OS Independent
Classifier: Natural Language :: English
Requires-Python: >=3.9
License-File: LICENSE
Requires-Dist: czekitout>=1.2.0
Requires-Dist: GitPython
Provides-Extra: tests
Requires-Dist: pytest-cov; extra == "tests"
Provides-Extra: examples
Provides-Extra: docs
Requires-Dist: sphinx<7; extra == "docs"
Requires-Dist: sphinx_rtd_theme; extra == "docs"
Requires-Dist: sphinx-autodoc-typehints; extra == "docs"
Requires-Dist: numpydoc; extra == "docs"
Requires-Dist: docutils; extra == "docs"
Provides-Extra: all
Requires-Dist: pylibtemplate[docs,examples,tests]; extra == "all"
Dynamic: license-file
